nonebot_plugin_hx_yinying/__init__.py
nonebot_plugin_hx_yinying/chat.py
nonebot_plugin_hx_yinying/config.py
nonebot_plugin_hx_yinying/report.py
nonebot_plugin_hx_yinying-1.4.11.dist-info/LICENSE
nonebot_plugin_hx_yinying-1.4.11.dist-info/METADATA
nonebot_plugin_hx_yinying-1.4.11.dist-info/WHEEL
nonebot_plugin_hx_yinying-1.4.11.dist-info/top_level.txt
nonebot_plugin_hx_yinying-1.4.11.dist-info/RECORD
