Metadata-Version: 2.1
Name: nonebot-plugin-hx-yinying
Version: 1.4.11
Summary: chat with yinying
Home-page: https://github.com/huanxin996/nonebot_plugin_hx-yinying
Author: Huan Xin
Author-email: mc.xiaolang@foxmail.com
Classifier: Programming Language :: Python :: 3
Classifier: License :: OSI Approved :: MIT License
Classifier: Operating System :: OS Independent
License-File: LICENSE
Requires-Dist: nonebot2>=2.2.1
Requires-Dist: ujson>=5.9.0
Requires-Dist: httpx>=0.27.0
Requires-Dist: nonebot-adapter-onebot>=2.4.3
Requires-Dist: nonebot_plugin_localstore>=0.6.0
Requires-Dist: pydantic>=1.10.12
Requires-Dist: requests>=2.31.0
Requires-Dist: nonebot_plugin_apscheduler>=0.4.0
Requires-Dist: nonebot_plugin_htmlrender>=0.3.0
Requires-Dist: pillow>=9.3.0
Requires-Dist: tqdm>=4.65.0
Requires-Dist: alibabacloud_imageaudit20191230>=2.0.5
